simple.v
module simple (in1, in2, in3, out1);

input in1;
input in2;
input in3;

output out1;

assign out1 = in1 && in2 && in3;

endmodule

simple_tb.v
`include "simple.v"

module simple_tb;
    reg a, b, c;
    wire out;

    simple s1(a, b, c, out);

    initial 
        begin
            $dumpfile("simple.vcd");
            $dumpvars(0, simple_tb);

            a = 0; b = 0; c = 0;
            #2
            a = 0; b = 0; c = 1;
            #2
            a = 0; b = 1; c = 0;
            #2
            a = 0; b = 1; c = 1;
            #2
            a = 1; b = 0; c = 0;
            #2
            a = 1; b = 0; c = 1;
            #2
            a = 1; b = 1; c = 0;
            #2
            a = 1; b = 1; c = 1;
            #2
            a = 0; b = 0; c = 0;
            #2
            a = 0; b = 0; c = 1;
            #2
            a = 0; b = 1; c = 0;
            #2
            a = 0; b = 1; c = 1;
            #2
            a = 1; b = 0; c = 0;
            #2
            a = 1; b = 0; c = 1;
            #2
            a = 1; b = 1; c = 0;
            #2
            a = 1; b = 1; c = 1;
        end

endmodule

simple.vcd
$date
	Fri Jun  9 22:16:42 2023
$end
$version
	Icarus Verilog
$end
$timescale
	1s
$end
$scope module simple_tb $end
$var wire 1 ! out $end
$var reg 1 " a $end
$var reg 1 # b $end
$var reg 1 $ c $end
$scope module s1 $end
$var wire 1 " in1 $end
$var wire 1 # in2 $end
$var wire 1 $ in3 $end
$var wire 1 ! out1 $end
$upscope $end
$upscope $end
$enddefinitions $end
#0
$dumpvars
0$
0#
0"
0!
$end
#2
1$
#4
0$
1#
#6
1$
#8
0$
0#
1"
#10
1$
#12
0$
1#
#14
1!
1$
#16
0!
0$
0#
0"
#18
1$
#20
0$
1#
#22
1$
#24
0$
0#
1"
#26
1$
#28
0$
1#
#30
1!
1$
